fairret/__init__.py
fairret/metric.py
fairret/utils.py
fairret/loss/__init__.py
fairret/loss/base.py
fairret/loss/projection.py
fairret/loss/violation.py
fairret/statistic/__init__.py
fairret/statistic/base.py
fairret/statistic/linear_fractional.py
fairret-0.1.3.dist-info/LICENSE
fairret-0.1.3.dist-info/METADATA
fairret-0.1.3.dist-info/WHEEL
fairret-0.1.3.dist-info/top_level.txt
fairret-0.1.3.dist-info/RECORD
