Metadata-Version: 2.1
Name: fairret
Version: 0.1.3
Summary: A fairness library in PyTorch.
Author-email: Maarten Buyl <maarten.buyl@ugent.be>, MaryBeth Defrance <marybeth.defrance@ugent.be>
License: MIT License
Keywords: fairness,machine-learning,ai,artificial-intelligence,pytorch,deep-learning,python,bias,fairness-ai,fairness-ml
Requires-Python: >=3.8
License-File: LICENSE
Requires-Dist: torch
Requires-Dist: numpy
